drftypegen/__init__.py
drftypegen/adapters.py
drftypegen/admin.py
drftypegen/apps.py
drftypegen/compilers.py
drftypegen/tests.py
drftypegen/management/__init__.py
drftypegen/management/commands/__init__.py
drftypegen/management/commands/genTSTypes.py
drftypegen/migrations/__init__.py
drftypegen-0.3.2.dist-info/LICENSE
drftypegen-0.3.2.dist-info/METADATA
drftypegen-0.3.2.dist-info/WHEEL
drftypegen-0.3.2.dist-info/top_level.txt
drftypegen-0.3.2.dist-info/RECORD
