Metadata-Version: 2.1
Name: drftypegen
Version: 0.3.2
Summary: An django app to generate type information for rest_framework.
Home-page: https://github.com/pypa/sampleproject
Author: Utsob Roy
Author-email: roy@codesign.com.bd
License: Mozilla Public License 2.0 (MPL 2.0)
Platform: UNKNOWN
Classifier: Framework :: Django
Classifier: Intended Audience :: Developers
Classifier: License :: OSI Approved :: Mozilla Public License 2.0 (MPL 2.0)
Classifier: Operating System :: OS Independent
Classifier: Programming Language :: Python
Requires-Python: >=3.6
Requires-Dist: djangorestframework
